{
    "itemID": "661bf1b62b235",
    "itemName": "Revolver R8 (StatTrak\u2122) | Carcasse",
    "itemURL": "https:\/\/steamcommunity.com\/market\/listings\/730\/StatTrak%E2%84%A2%20R8%20Revolver%20%7C%20Bone%20Forged%20%28Field-Tested%29",
    "itemURLJSON": "https:\/\/steamcommunity.com\/market\/priceoverview\/?country=US&currency=3&appid=730&market_hash_name=StatTrak%E2%84%A2+R8+Revolver+%7C+Bone+Forged+%28Field-Tested%29",
    "itemQuality": "Field-Tested",
    "itemPriceDefault": "0.15",
    "itemPriceActual": "0.14",
    "itemType": "\u20ac",
    "track": [
        [
            {
                "date": "14\/04\/2024",
                "price": "0.14"
            }
        ]
    ]
}